hadoop_yarn_cluster_checker_model
