Metadata-Version: 2.1
Name: HadoopYarnClusterCheckerLib
Version: 49
Summary: fires an event if your hadoop-yarn cluster becomes empty
Home-page: https://bitbucket.org/ffischer/hadoop-yarn-cluster-checker-model
Author: fafi84
Author-email: ffischer1984@googlemail.com
License: UNKNOWN
Platform: UNKNOWN
Classifier: Programming Language :: Python :: 3
Classifier: License :: OSI Approved :: MIT License
Classifier: Operating System :: OS Independent
